meow/webs/__init__.py
meow/webs/app.py
meow/webs/codecs.py
meow/webs/conneg.py
meow/webs/datastructures.py
meow/webs/exceptions.py
meow/webs/handlers.py
meow/webs/http.py
meow/webs/py.typed
meow/webs/router.py
meow/webs/settings.py
meow/webs/staticfiles.py
meow/webs/templates.py
meow/webs/test.py
meow/webs/utils.py
meow/webs/validation.py
meow/webs/wsgi.py
meow.webs-1.0.3.dist-info/LICENSE
meow.webs-1.0.3.dist-info/METADATA
meow.webs-1.0.3.dist-info/WHEEL
meow.webs-1.0.3.dist-info/top_level.txt
meow.webs-1.0.3.dist-info/RECORD
