Metadata-Version: 2.1
Name: meow.webs
Version: 1.0.3
Summary: Expressive WEB apiS
Home-page: https://github.com/aachurin/meow.webs
Author: Andrey Churin
Maintainer: Andrey Churin
Maintainer-email: aachurin@gmail.com
License: MIT
Platform: UNKNOWN
Classifier: Development Status :: 5 - Production/Stable
Classifier: Environment :: Web Environment
Classifier: Intended Audience :: Developers
Classifier: License :: OSI Approved :: MIT License
Classifier: Operating System :: OS Independent
Classifier: Topic :: Internet :: WWW/HTTP
Classifier: Programming Language :: Python :: 3 :: Only
Classifier: Programming Language :: Python :: 3.8
Classifier: Programming Language :: Python :: 3.9
Requires-Dist: jinja2
Requires-Dist: werkzeug
Requires-Dist: whitenoise
Requires-Dist: meow.di
Requires-Dist: meow.validators
